jaxdf/__init__.py
jaxdf/conv.py
jaxdf/core.py
jaxdf/discretization.py
jaxdf/geometry.py
jaxdf/logger.py
jaxdf/mods.py
jaxdf/operators/__init__.py
jaxdf/operators/differential.py
jaxdf/operators/dummy.py
jaxdf/operators/functions.py
jaxdf/operators/linear_algebra.py
jaxdf/operators/magic.py
jaxdf/signatures.py
jaxdf/util.py
jaxdf-0.2.8.dist-info/LICENSE
jaxdf-0.2.8.dist-info/METADATA
jaxdf-0.2.8.dist-info/WHEEL
jaxdf-0.2.8.dist-info/RECORD
